keyring_wsl_host-0.1.5.dist-info/METADATA
keyring_wsl_host-0.1.5.dist-info/WHEEL
keyring_wsl_host-0.1.5.dist-info/entry_points.txt
keyring_wsl_host/__init__.py
keyring_wsl_host-0.1.5.dist-info/RECORD
